rtl/pe.v
module pe (
        input  wire clk,
	input  wire rst_n,

        input  wire [3:0] a_in,
        input  wire [3:0] b,
        input  wire [8:0] cin,

        input  wire clr_psum,

        output reg [3:0] a_out,
        output wire [8:0] cout
);

        reg [8:0] psum;

        always @(posedge clk or negedge rst_n) begin
                if (!rst_n) begin
                        psum <= 9'b0;
                        a_out <= 4'b0;
                end
                else begin
                        a_out <= a_in;

                        if (clr_psum)
                                psum <= 9'b0;
                        else
                                psum <= cin + (a_in * b);
                end
        end

        assign cout = psum;

endmodule

rtl/systolic_datapath.v
module systolic_datapath (
        input clk,
        input rst_n,

        input [3:0] a_pe11,
        input [3:0] a_pe21,

        input [3:0] b11,
        input [3:0] b12,
        input [3:0] b21,
        input [3:0] b22,

        input clr_pe21,
        input clr_pe22,

        output wire [8:0] c11,
        output wire [8:0] c12,
        output wire [8:0] c21,
        output wire [8:0] c22
);

        wire [3:0] wa1;
        wire [3:0] wa2;

        pe PE11 (clk, rst_n, a_pe11, b11, 9'b0, 1'b0, wa1, c11);
        pe PE12 (clk, rst_n, wa1, b12, 9'b0, 1'b0, , c12);
        pe PE21 (clk, rst_n, a_pe21, b21, c11, clr_pe21, wa2, c21);
        pe PE22 (clk, rst_n, wa2, b22, c12, clr_pe22, , c22);

endmodule

rtl/systolic_controller.v
module systolic_controller (
        input clk,
        input rst_n,
        input in_valid,

        input [3:0] a11,
        input [3:0] a12,
        input [3:0] a21,
        input [3:0] a22,

        output reg [3:0] a_pe11,
        output reg [3:0] a_pe21,

        output reg clr_pe21,
        output reg clr_pe22,

        output reg out_valid
);

        reg [2:0] cycle;
        reg active;

        always @(posedge clk or negedge rst_n) begin
                if (!rst_n) begin
                        cycle <= 3'd0;
                        active <= 1'b0;
                        a_pe11 <= 4'd0;
                        a_pe21 <= 4'd0;
                        clr_pe21 <= 1'b0;
                        clr_pe22<= 1'b0;
                        out_valid <= 1'b0;
                end
                else begin
                        clr_pe21 <= 1'b0;
                        clr_pe22 <= 1'b0;
                        out_valid <= 1'b0;

                        if (in_valid && !active) begin
                                active <= 1'b1;
                                cycle<= 3'd0;
                        end
                        else if (active) begin
                                cycle <= cycle + 3'd1;
                                if (cycle == 3'd4)
                                        active <= 1'b0;
                        end

                        if (active) begin
                                case (cycle)
                                        3'd0: begin
                                                a_pe11 <= a11;
                                                a_pe21 <= 4'd0;
                                        end
                                        3'd1: begin
                                                a_pe11 <= a21;
                                                a_pe21 <= a12;
                                        end
                                        3'd2: begin
			        		a_pe11 <= 4'd0;
			        		a_pe21 <= a22;
					end

		        		3'd3: begin
						a_pe11 <= 4'd0;
						a_pe21 <= 4'd0;
						clr_pe21 <= 1'b1;
					end

					3'd4: begin
						clr_pe22 <= 1'b1;
						out_valid <= 1'b1;
					end

                                endcase
                        end
                        else begin
                                a_pe11 <= 4'd0;
                                a_pe21 <= 4'd0;
                        end
                end
        end

endmodule

rtl/systolic.v
module systolic (
        input clk,
        input rst_n,
        input in_valid,

        input [3:0] a11,
        input [3:0] a12,
        input [3:0] a21,
        input [3:0] a22,

        input [3:0] b11,
        input [3:0] b12,
        input [3:0] b21,
        input [3:0] b22,

        output wire [8:0] c11,
        output wire [8:0] c12,
        output wire [8:0] c21,
        output wire [8:0] c22,

        output wire out_valid
);

        wire [3:0] a_pe11;
        wire [3:0] a_pe21;

        wire clr_pe21;
        wire clr_pe22;

        systolic_controller controller (
                clk, rst_n, in_valid, a11, a12, a21, a22, a_pe11, a_pe21, clr_pe21, clr_pe22, out_valid
        );

        systolic_datapath datapath (
                clk, rst_n, a_pe11, a_pe21, b11, b12, b21, b22, clr_pe21, clr_pe22, c11, c12, c21, c22
        );

endmodule

rtl/tb_systolic.v
module tb_systolic;

        reg clk;
        reg rst_n;
        reg in_valid;

        reg [3:0] a11;
        reg [3:0] a12;
        reg [3:0] a21;
        reg [3:0] a22;

        reg [3:0] b11;
        reg [3:0] b12;
        reg [3:0] b21;
        reg [3:0] b22;

        wire [8:0] c11;
        wire [8:0] c12;
        wire [8:0] c21;
        wire [8:0] c22;

        wire out_valid;

        systolic dut (
                clk, rst_n, in_valid, a11, a12, a21, a22, b11, b12, b21, b22, c11, c12, c21, c22, out_valid
        );

        always #5 clk = ~clk;

        initial begin
        	$dumpfile("tb_systolic.vcd");
                $dumpvars(0, tb_systolic);
                
                clk = 0;
                rst_n = 0;
                in_valid = 0;

                $monitor(
                        "T=%0t | cycle=%0d | a_pe11=%0d a_pe21=%0d | c11=%0d c12=%0d c21=%0d c22=%0d | out_valid=%b",
                        $time, dut.controller.cycle, dut.a_pe11, dut.a_pe21, c11, c12, c21, c22, out_valid
                );

                a11 = 0; a12 = 0; a21 = 0; a22 = 0;
                b11 = 0; b12 = 0; b21 = 0; b22 = 0;

                #20;
                rst_n = 1;

                #10;

                a11 = 1;  a12 = 2;
                a21 = 3;  a22 = 4;

                b11 = 5;  b12 = 6;
                b21 = 7;  b22 = 8;

                in_valid = 1;
                #10;
                in_valid = 0;

                wait(out_valid);

                #20;
                $finish;
        end

endmodule

results/tb_systolic.vcd
$date
	Thu Mar 26 22:09:52 2026
$end
$version
	Icarus Verilog
$end
$timescale
	1s
$end
$scope module tb_systolic $end
$var wire 1 ! out_valid $end
$var wire 9 " c22 [8:0] $end
$var wire 9 # c21 [8:0] $end
$var wire 9 $ c12 [8:0] $end
$var wire 9 % c11 [8:0] $end
$var reg 4 & a11 [3:0] $end
$var reg 4 ' a12 [3:0] $end
$var reg 4 ( a21 [3:0] $end
$var reg 4 ) a22 [3:0] $end
$var reg 4 * b11 [3:0] $end
$var reg 4 + b12 [3:0] $end
$var reg 4 , b21 [3:0] $end
$var reg 4 - b22 [3:0] $end
$var reg 1 . clk $end
$var reg 1 / in_valid $end
$var reg 1 0 rst_n $end
$scope module dut $end
$var wire 4 1 a11 [3:0] $end
$var wire 4 2 a12 [3:0] $end
$var wire 4 3 a21 [3:0] $end
$var wire 4 4 a22 [3:0] $end
$var wire 4 5 b11 [3:0] $end
$var wire 4 6 b12 [3:0] $end
$var wire 4 7 b21 [3:0] $end
$var wire 4 8 b22 [3:0] $end
$var wire 1 . clk $end
$var wire 1 / in_valid $end
$var wire 1 0 rst_n $end
$var wire 1 ! out_valid $end
$var wire 1 9 clr_pe22 $end
$var wire 1 : clr_pe21 $end
$var wire 9 ; c22 [8:0] $end
$var wire 9 < c21 [8:0] $end
$var wire 9 = c12 [8:0] $end
$var wire 9 > c11 [8:0] $end
$var wire 4 ? a_pe21 [3:0] $end
$var wire 4 @ a_pe11 [3:0] $end
$scope module controller $end
$var wire 4 A a11 [3:0] $end
$var wire 4 B a12 [3:0] $end
$var wire 4 C a21 [3:0] $end
$var wire 4 D a22 [3:0] $end
$var wire 1 . clk $end
$var wire 1 / in_valid $end
$var wire 1 0 rst_n $end
$var reg 4 E a_pe11 [3:0] $end
$var reg 4 F a_pe21 [3:0] $end
$var reg 1 G active $end
$var reg 1 : clr_pe21 $end
$var reg 1 9 clr_pe22 $end
$var reg 3 H cycle [2:0] $end
$var reg 1 ! out_valid $end
$upscope $end
$scope module datapath $end
$var wire 4 I a_pe11 [3:0] $end
$var wire 4 J a_pe21 [3:0] $end
$var wire 4 K b11 [3:0] $end
$var wire 4 L b12 [3:0] $end
$var wire 4 M b21 [3:0] $end
$var wire 4 N b22 [3:0] $end
$var wire 1 . clk $end
$var wire 1 : clr_pe21 $end
$var wire 1 9 clr_pe22 $end
$var wire 1 0 rst_n $end
$var wire 4 O wa2 [3:0] $end
$var wire 4 P wa1 [3:0] $end
$var wire 9 Q c22 [8:0] $end
$var wire 9 R c21 [8:0] $end
$var wire 9 S c12 [8:0] $end
$var wire 9 T c11 [8:0] $end
$scope module PE11 $end
$var wire 4 U a_in [3:0] $end
$var wire 4 V b [3:0] $end
$var wire 9 W cin [8:0] $end
$var wire 1 . clk $end
$var wire 1 X clr_psum $end
$var wire 9 Y cout [8:0] $end
$var wire 1 0 rst_n $end
$var reg 4 Z a_out [3:0] $end
$var reg 9 [ psum [8:0] $end
$upscope $end
$scope module PE12 $end
$var wire 4 \ a_in [3:0] $end
$var wire 4 ] b [3:0] $end
$var wire 9 ^ cin [8:0] $end
$var wire 1 . clk $end
$var wire 1 _ clr_psum $end
$var wire 9 ` cout [8:0] $end
$var wire 1 0 rst_n $end
$var reg 4 a a_out [3:0] $end
$var reg 9 b psum [8:0] $end
$upscope $end
$scope module PE21 $end
$var wire 4 c a_in [3:0] $end
$var wire 4 d b [3:0] $end
$var wire 9 e cin [8:0] $end
$var wire 1 . clk $end
$var wire 1 : clr_psum $end
$var wire 9 f cout [8:0] $end
$var wire 1 0 rst_n $end
$var reg 4 g a_out [3:0] $end
$var reg 9 h psum [8:0] $end
$upscope $end
$scope module PE22 $end
$var wire 4 i a_in [3:0] $end
$var wire 4 j b [3:0] $end
$var wire 9 k cin [8:0] $end
$var wire 1 . clk $end
$var wire 1 9 clr_psum $end
$var wire 9 l cout [8:0] $end
$var wire 1 0 rst_n $end
$var reg 4 m a_out [3:0] $end
$var reg 9 n psum [8:0] $end
$upscope $end
$upscope $end
$upscope $end
$upscope $end
$enddefinitions $end
$comment Show the parameter values. $end
$dumpall
$end
#0
$dumpvars
b0 n
b0 m
b0 l
b0 k
b0 j
b0 i
b0 h
b0 g
b0 f
b0 e
b0 d
b0 c
b0 b
b0 a
b0 `
0_
b0 ^
b0 ]
b0 \
b0 [
b0 Z
b0 Y
0X
b0 W
b0 V
b0 U
b0 T
b0 S
b0 R
b0 Q
b0 P
b0 O
b0 N
b0 M
b0 L
b0 K
b0 J
b0 I
b0 H
0G
b0 F
b0 E
b0 D
b0 C
b0 B
b0 A
b0 @
b0 ?
b0 >
b0 =
b0 <
b0 ;
0:
09
b0 8
b0 7
b0 6
b0 5
b0 4
b0 3
b0 2
b0 1
00
0/
0.
b0 -
b0 ,
b0 +
b0 *
b0 )
b0 (
b0 '
b0 &
b0 %
b0 $
b0 #
b0 "
0!
$end
#5
1.
#10
0.
#15
1.
#20
0.
10
#25
1.
#30
0.
1/
b1000 -
b1000 8
b1000 N
b1000 j
b111 ,
b111 7
b111 M
b111 d
b110 +
b110 6
b110 L
b110 ]
b101 *
b101 5
b101 K
b101 V
b100 )
b100 4
b100 D
b11 (
b11 3
b11 C
b10 '
b10 2
b10 B
b1 &
b1 1
b1 A
#35
1G
1.
#40
0.
0/
#45
b1 @
b1 E
b1 I
b1 U
b1 H
1.
#50
0.
#55
b10 ?
b10 F
b10 J
b10 c
b11 @
b11 E
b11 I
b11 U
b10 H
b101 %
b101 >
b101 T
b101 Y
b101 e
b101 [
b1 P
b1 Z
b1 \
1.
#60
0.
#65
b10011 #
b10011 <
b10011 R
b10011 f
b10011 h
b10 O
b10 g
b10 i
b110 $
b110 =
b110 S
b110 `
b110 k
b110 b
b1 a
b1111 %
b1111 >
b1111 T
b1111 Y
b1111 e
b1111 [
b11 P
b11 Z
b11 \
b100 ?
b100 F
b100 J
b100 c
b0 @
b0 E
b0 I
b0 U
b11 H
1.
#70
0.
#75
1:
b0 ?
b0 F
b0 J
b0 c
b100 H
b0 %
b0 >
b0 T
b0 Y
b0 e
b0 [
b0 P
b0 Z
b0 \
b10010 $
b10010 =
b10010 S
b10010 `
b10010 k
b10010 b
b11 a
b101011 #
b101011 <
b101011 R
b101011 f
b101011 h
b100 O
b100 g
b100 i
b10110 "
b10110 ;
b10110 Q
b10110 l
b10110 n
b10 m
1.
#80
0.
#85
b110010 "
b110010 ;
b110010 Q
b110010 l
b110010 n
b100 m
b0 #
b0 <
b0 R
b0 f
b0 h
b0 O
b0 g
b0 i
b0 $
b0 =
b0 S
b0 `
b0 k
b0 b
b0 a
1!
19
0G
b101 H
0:
1.
#90
0.
#95
0!
09
b0 "
b0 ;
b0 Q
b0 l
b0 n
b0 m
1.
